cigen/__init__.py
cigen/__main__.py
cigen/adapter/__init__.py
cigen/adapter/input/__init__.py
cigen/adapter/input/docker_command/__init__.py
cigen/adapter/input/docker_command/docker_group.py
cigen/adapter/input/github_command/__init__.py
cigen/adapter/input/github_command/action_command.py
cigen/adapter/input/github_command/github_action_group.py
cigen/adapter/input/github_command/go_command.py
cigen/adapter/input/github_command/go_command_test.py
cigen/adapter/input/github_command/nodejs_command.py
cigen/adapter/input/github_command/nodejs_command_test.py
cigen/adapter/input/gitlab_command/__init__.py
cigen/adapter/input/gitlab_command/gitlab_group.py
cigen/adapter/input/jenkins_command/__init__.py
cigen/adapter/input/jenkins_command/jenkins_group.py
cigen/adapter/output/__init__.py
cigen/adapter/output/github_out/__init__.py
cigen/adapter/output/github_out/file_action.py
cigen/cmd/__init__.py
cigen/cmd/command.py
cigen/core/__init__.py
cigen/core/github/__init__.py
cigen/core/github/base_action.py
cigen/core/github/github_action.py
cigen/core/github/github_action_test.py
cigen/core/github/go_action.py
cigen/core/github/go_action_test.py
cigen/core/github/nodejs_action.py
cigen/core/github/nodejs_action_test.py
ci_generator-0.2.0.dist-info/LICENSE
ci_generator-0.2.0.dist-info/METADATA
ci_generator-0.2.0.dist-info/WHEEL
ci_generator-0.2.0.dist-info/entry_points.txt
ci_generator-0.2.0.dist-info/top_level.txt
ci_generator-0.2.0.dist-info/RECORD
