Metadata-Version: 2.1
Name: ci-generator
Version: 0.2.0
Summary: A Continuous Integration Generator
Home-page: https://github.com/Paulo-Lopes-Estevao/ci-generator
Author: Paulo Lopes Estevao
License: MIT
License-File: LICENSE
Requires-Dist: Click
Requires-Dist: PyYAML
Requires-Dist: rich
